braincowboys/__init__.py
braincowboys/sensors/__init__.py
braincowboys/sensors/retina.py
braincowboys-0.0.1.dist-info/METADATA
braincowboys-0.0.1.dist-info/WHEEL
braincowboys-0.0.1.dist-info/top_level.txt
braincowboys-0.0.1.dist-info/RECORD
