Metadata-Version: 2.1
Name: braincowboys
Version: 0.0.1
Summary: Brain Computations in Python
Home-page: https://github.com/gialdetti/braincowboys/
Author: Eyal Gal
Author-email: eyalgl@gmail.com
License: UNKNOWN
Platform: UNKNOWN
Classifier: Programming Language :: Python :: 3.7
